main.py
crawlerugo/crawler.py
crawlerugo-0.0.4.dist-info/licenses/LICENCE.md
crawlerugo-0.0.4.dist-info/METADATA
crawlerugo-0.0.4.dist-info/WHEEL
crawlerugo-0.0.4.dist-info/top_level.txt
crawlerugo-0.0.4.dist-info/RECORD
